evaluation/__init__.py
evaluation/metric_stability.py
evaluation/ml_utility.py
evaluation/privacy_metrics.py
evaluation/progressive_sampler.py
evaluation/sdmetrics_evaluation.py
evaluation/tstr_correlation.py
generators/Disc_KAN_CTGAN.py
generators/Gen_KAN_CTGAN.py
generators/Hybrid_CTGAN.py
generators/Hybrid_TVAE.py
generators/KAN.py
generators/KAN_CTGAN.py
generators/KAN_TVAE.py
generators/__init__.py
generators/base_generator.py
generators/ctgan_model.py
generators/gaussian_copula.py
generators/kan_ctgan_model.py
generators/kan_tvae_model.py
generators/smote_generator.py
generators/tvae_model.py
scripts/__init__.py
scripts/config.yaml
scripts/download_datasets.py
scripts/download_low_resource_datasets.py
scripts/generate_latex_tables.py
scripts/make_release.py
scripts/run_benchmark.py
scripts/run_meta_evaluation.py
scripts/statistical_analysis.py
scripts/visualize_meta_evaluation.py
scripts/visualize_results.py
synth_data_eval-0.1.6.dist-info/licenses/LICENSE
synth_data_eval-0.1.6.dist-info/METADATA
synth_data_eval-0.1.6.dist-info/WHEEL
synth_data_eval-0.1.6.dist-info/entry_points.txt
synth_data_eval-0.1.6.dist-info/top_level.txt
synth_data_eval-0.1.6.dist-info/RECORD
