Metadata-Version: 2.4
Name: synth-data-eval
Version: 0.1.6
Summary: Comprehensive evaluation framework for tabular synthetic data generators
Author-email: Ahmed Fouad LAGHA <ahmed.lagha@inf.elte.hu>, Izsa Regina Mária <bnbq2z@inf.elte.hu>, Zakarya Farou <zakaryafarou@inf.elte.hu>
Maintainer-email: Ahmed Fouad LAGHA <ahmed.lagha@inf.elte.hu>, Izsa Regina Mária <bnbq2z@inf.elte.hu>, Zakarya Farou <zakaryafarou@inf.elte.hu>
License: MIT License
Project-URL: Homepage, https://github.com/ahmed-fouad-lagha/synth-data-eval
Project-URL: Documentation, https://github.com/ahmed-fouad-lagha/synth-data-eval#readme
Project-URL: Repository, https://github.com/ahmed-fouad-lagha/synth-data-eval
Project-URL: Issues, https://github.com/ahmed-fouad-lagha/synth-data-eval/issues
Project-URL: Changelog, https://github.com/ahmed-fouad-lagha/synth-data-eval/blob/main/CHANGELOG.md
Keywords: synthetic-data,machine-learning,evaluation,tabular-data,ctgan,privacy,data-generation
Classifier: Development Status :: 3 - Alpha
Classifier: Intended Audience :: Science/Research
Classifier: License :: OSI Approved :: MIT License
Classifier: Operating System :: OS Independent
Classifier: Programming Language :: Python :: 3
Classifier: Programming Language :: Python :: 3.10
Classifier: Programming Language :: Python :: 3.11
Classifier: Programming Language :: Python :: 3.12
Classifier: Topic :: Scientific/Engineering :: Artificial Intelligence
Requires-Python: <3.13,>=3.10
License-File: LICENSE
Requires-Dist: numpy<2.0.0,>=1.21.0
Requires-Dist: pandas<3.0.0,>=1.3.0
Requires-Dist: scikit-learn<2.0.0,>=1.0.0
Requires-Dist: scipy<2.0.0,>=1.7.0
Requires-Dist: sdv<2.0.0,>=1.2.0
Requires-Dist: ctgan<1.0.0,>=0.7.0
Requires-Dist: sdmetrics<1.0.0,>=0.12.0
Requires-Dist: table-evaluator>=1.4.0
Requires-Dist: pyyaml>=6.0
Requires-Dist: tqdm>=4.62.0
Requires-Dist: joblib>=1.1.0
Requires-Dist: matplotlib>=3.5.0
Requires-Dist: seaborn>=0.12.0
Requires-Dist: plotly>=5.10.0
Requires-Dist: loguru>=0.6.0
Requires-Dist: xlrd>=2.0.0
Provides-Extra: dev
Requires-Dist: pytest>=7.0.0; extra == "dev"
Requires-Dist: pytest-cov>=3.0.0; extra == "dev"
Requires-Dist: pytest-xdist>=2.5.0; extra == "dev"
Requires-Dist: black>=22.0.0; extra == "dev"
Requires-Dist: flake8>=4.0.0; extra == "dev"
Requires-Dist: isort>=5.10.0; extra == "dev"
Requires-Dist: mypy>=0.990; extra == "dev"
Requires-Dist: pre-commit>=2.20.0; extra == "dev"
Provides-Extra: notebooks
Requires-Dist: jupyter>=1.0.0; extra == "notebooks"
Requires-Dist: ipykernel>=6.0.0; extra == "notebooks"
Requires-Dist: ipywidgets>=8.0.0; extra == "notebooks"
Requires-Dist: notebook>=6.5.0; extra == "notebooks"
Provides-Extra: synthcity
Requires-Dist: synthcity>=0.2.0; extra == "synthcity"
Provides-Extra: docs
Requires-Dist: sphinx>=5.0.0; extra == "docs"
Requires-Dist: sphinx-rtd-theme>=1.0.0; extra == "docs"
Requires-Dist: sphinxcontrib-napoleon>=0.7; extra == "docs"
Provides-Extra: all
Requires-Dist: pytest>=7.0.0; extra == "all"
Requires-Dist: pytest-cov>=3.0.0; extra == "all"
Requires-Dist: black>=22.0.0; extra == "all"
Requires-Dist: flake8>=4.0.0; extra == "all"
Requires-Dist: isort>=5.10.0; extra == "all"
Requires-Dist: jupyter>=1.0.0; extra == "all"
Requires-Dist: synthcity>=0.2.0; extra == "all"
Requires-Dist: sphinx>=5.0.0; extra == "all"
Dynamic: license-file
